README.rst
setup.cfg
setup.py
terseout.py
nose_terse_output.egg-info/PKG-INFO
nose_terse_output.egg-info/SOURCES.txt
nose_terse_output.egg-info/dependency_links.txt
nose_terse_output.egg-info/entry_points.txt
nose_terse_output.egg-info/requires.txt
nose_terse_output.egg-info/top_level.txt