Metadata-Version: 1.0
Name: nose-terse-output
Version: 1.1.0
Summary: Terse output from your nose tests
Home-page: https://github.com/joakimkarlsson/nose-terse-output
Author: Joakim Karlsson
Author-email: joakim@jkarlsson.com
License: UNKNOWN
Keywords: unit testing,nose
Platform: UNKNOWN
